<Applications>
    <AVBApplication name="AVB_1">
        <AVBClass>CLASS_A</AVBClass>
        <PayloadSize>852</PayloadSize>
        <NoOfFrames>1</NoOfFrames>
        <Source name="ES_FRONT_CAM" />
        <Destinations>
            <Dest name="ES_CTRL2" />
        </Destinations>
        <Deadline>2000</Deadline>
    </AVBApplication>
    <AVBApplication name="AVB_2">
        <AVBClass>CLASS_A</AVBClass>
        <PayloadSize>1472</PayloadSize>
        <NoOfFrames>1</NoOfFrames>
        <Source name="ES_FRONT_CAM" />
        <Destinations>
            <Dest name="ES_CTRL1" />
        </Destinations>
        <Deadline>2000</Deadline>
    </AVBApplication>
    <AVBApplication name="AVB_3">
        <AVBClass>CLASS_A</AVBClass>
        <PayloadSize>611</PayloadSize>
        <NoOfFrames>1</NoOfFrames>
        <Source name="ES_REAR_CAM" />
        <Destinations>
            <Dest name="ES_CTRL2" />
        </Destinations>
        <Deadline>2000</Deadline>
    </AVBApplication>
    <AVBApplication name="AVB_4">
        <AVBClass>CLASS_A</AVBClass>
        <PayloadSize>644</PayloadSize>
        <NoOfFrames>1</NoOfFrames>
        <Source name="ES_REAR_CAM" />
        <Destinations>
            <Dest name="ES_CTRL1" />
        </Destinations>
        <Deadline>2000</Deadline>
    </AVBApplication>
    <AVBApplication name="AVB_5">
        <AVBClass>CLASS_A</AVBClass>
        <PayloadSize>1291</PayloadSize>
        <NoOfFrames>1</NoOfFrames>
        <Source name="ES_FRONT_SVCAM" />
        <Destinations>
            <Dest name="ES_CTRL1" />
        </Destinations>
        <Deadline>2000</Deadline>
    </AVBApplication>
    <AVBApplication name="AVB_6">
        <AVBClass>CLASS_A</AVBClass>
        <PayloadSize>147</PayloadSize>
        <NoOfFrames>1</NoOfFrames>
        <Source name="ES_LEFT_SVCAM" />
        <Destinations>
            <Dest name="ES_CTRL1" />
        </Destinations>
        <Deadline>2000</Deadline>
    </AVBApplication>
    <AVBApplication name="AVB_7">
        <AVBClass>CLASS_A</AVBClass>
        <PayloadSize>1173</PayloadSize>
        <NoOfFrames>1</NoOfFrames>
        <Source name="ES_RIGHT_SVCAM" />
        <Destinations>
            <Dest name="ES_CTRL1" />
        </Destinations>
        <Deadline>2000</Deadline>
    </AVBApplication>
    <AVBApplication name="AVB_8">
        <AVBClass>CLASS_A</AVBClass>
        <PayloadSize>970</PayloadSize>
        <NoOfFrames>1</NoOfFrames>
        <Source name="ES_REAR_SVCAM" />
        <Destinations>
            <Dest name="ES_CTRL1" />
        </Destinations>
        <Deadline>2000</Deadline>
    </AVBApplication>
    <AVBApplication name="AVB_9">
        <AVBClass>CLASS_A</AVBClass>
        <PayloadSize>1366</PayloadSize>
        <NoOfFrames>1</NoOfFrames>
        <Source name="ES_FRONT_RAD" />
        <Destinations>
            <Dest name="ES_CTRL1" />
        </Destinations>
        <Deadline>2000</Deadline>
    </AVBApplication>
    <AVBApplication name="AVB_10">
        <AVBClass>CLASS_A</AVBClass>
        <PayloadSize>438</PayloadSize>
        <NoOfFrames>1</NoOfFrames>
        <Source name="ES_FRONT_RAD" />
        <Destinations>
            <Dest name="ES_CTRL2" />
        </Destinations>
        <Deadline>2000</Deadline>
    </AVBApplication>
    <AVBApplication name="AVB_11">
        <AVBClass>CLASS_A</AVBClass>
        <PayloadSize>740</PayloadSize>
        <NoOfFrames>1</NoOfFrames>
        <Source name="ES_LEFT_FRONT_RAD" />
        <Destinations>
            <Dest name="ES_CTRL1" />
        </Destinations>
        <Deadline>2000</Deadline>
    </AVBApplication>
    <AVBApplication name="AVB_12">
        <AVBClass>CLASS_A</AVBClass>
        <PayloadSize>62</PayloadSize>
        <NoOfFrames>1</NoOfFrames>
        <Source name="ES_LEFT_FRONT_RAD" />
        <Destinations>
            <Dest name="ES_CTRL2" />
        </Destinations>
        <Deadline>2000</Deadline>
    </AVBApplication>
    <AVBApplication name="AVB_13">
        <AVBClass>CLASS_A</AVBClass>
        <PayloadSize>107</PayloadSize>
        <NoOfFrames>1</NoOfFrames>
        <Source name="ES_RIGHT_FRONT_RAD" />
        <Destinations>
            <Dest name="ES_CTRL1" />
        </Destinations>
        <Deadline>2000</Deadline>
    </AVBApplication>
    <AVBApplication name="AVB_14">
        <AVBClass>CLASS_A</AVBClass>
        <PayloadSize>314</PayloadSize>
        <NoOfFrames>1</NoOfFrames>
        <Source name="ES_RIGHT_FRONT_RAD" />
        <Destinations>
            <Dest name="ES_CTRL2" />
        </Destinations>
        <Deadline>2000</Deadline>
    </AVBApplication>
    <AVBApplication name="AVB_15">
        <AVBClass>CLASS_A</AVBClass>
        <PayloadSize>61</PayloadSize>
        <NoOfFrames>1</NoOfFrames>
        <Source name="ES_LEFT_REAR_RAD" />
        <Destinations>
            <Dest name="ES_CTRL1" />
        </Destinations>
        <Deadline>2000</Deadline>
    </AVBApplication>
    <AVBApplication name="AVB_16">
        <AVBClass>CLASS_A</AVBClass>
        <PayloadSize>1355</PayloadSize>
        <NoOfFrames>1</NoOfFrames>
        <Source name="ES_LEFT_REAR_RAD" />
        <Destinations>
            <Dest name="ES_CTRL2" />
        </Destinations>
        <Deadline>2000</Deadline>
    </AVBApplication>
    <AVBApplication name="AVB_17">
        <AVBClass>CLASS_A</AVBClass>
        <PayloadSize>120</PayloadSize>
        <NoOfFrames>1</NoOfFrames>
        <Source name="ES_RIGHT_REAR_RAD" />
        <Destinations>
            <Dest name="ES_CTRL2" />
        </Destinations>
        <Deadline>2000</Deadline>
    </AVBApplication>
    <AVBApplication name="AVB_18">
        <AVBClass>CLASS_A</AVBClass>
        <PayloadSize>578</PayloadSize>
        <NoOfFrames>1</NoOfFrames>
        <Source name="ES_RIGHT_REAR_RAD" />
        <Destinations>
            <Dest name="ES_CTRL1" />
        </Destinations>
        <Deadline>2000</Deadline>
    </AVBApplication>
    <AVBApplication name="AVB_19">
        <AVBClass>CLASS_A</AVBClass>
        <PayloadSize>459</PayloadSize>
        <NoOfFrames>1</NoOfFrames>
        <Source name="ES_REAR_RAD" />
        <Destinations>
            <Dest name="ES_CTRL2" />
        </Destinations>
        <Deadline>2000</Deadline>
    </AVBApplication>
    <AVBApplication name="AVB_20">
        <AVBClass>CLASS_A</AVBClass>
        <PayloadSize>622</PayloadSize>
        <NoOfFrames>1</NoOfFrames>
        <Source name="ES_REAR_RAD" />
        <Destinations>
            <Dest name="ES_CTRL1" />
        </Destinations>
        <Deadline>2000</Deadline>
    </AVBApplication>
    <AVBApplication name="AVB_21">
        <AVBClass>CLASS_A</AVBClass>
        <PayloadSize>1080</PayloadSize>
        <NoOfFrames>1</NoOfFrames>
        <Source name="ES_CTRL1" />
        <Destinations>
            <Dest name="ES_REAR_RAD" />
        </Destinations>
        <Deadline>2000</Deadline>
    </AVBApplication>
    <AVBApplication name="AVB_22">
        <AVBClass>CLASS_A</AVBClass>
        <PayloadSize>225</PayloadSize>
        <NoOfFrames>1</NoOfFrames>
        <Source name="ES_CTRL1" />
        <Destinations>
            <Dest name="ES_FRONT_RAD" />
        </Destinations>
        <Deadline>2000</Deadline>
    </AVBApplication>
    <AVBApplication name="AVB_23">
        <AVBClass>CLASS_A</AVBClass>
        <PayloadSize>1183</PayloadSize>
        <NoOfFrames>1</NoOfFrames>
        <Source name="ES_CTRL1" />
        <Destinations>
            <Dest name="ES_FRONT_CAM" />
        </Destinations>
        <Deadline>2000</Deadline>
    </AVBApplication>
    <AVBApplication name="AVB_24">
        <AVBClass>CLASS_A</AVBClass>
        <PayloadSize>886</PayloadSize>
        <NoOfFrames>1</NoOfFrames>
        <Source name="ES_CTRL1" />
        <Destinations>
            <Dest name="ES_REAR_CAM" />
        </Destinations>
        <Deadline>2000</Deadline>
    </AVBApplication>
    <AVBApplication name="AVB_25">
        <AVBClass>CLASS_A</AVBClass>
        <PayloadSize>242</PayloadSize>
        <NoOfFrames>1</NoOfFrames>
        <Source name="ES_CTRL2" />
        <Destinations>
            <Dest name="ES_FRONT_CAM" />
        </Destinations>
        <Deadline>2000</Deadline>
    </AVBApplication>
    <AVBApplication name="AVB_26">
        <AVBClass>CLASS_A</AVBClass>
        <PayloadSize>358</PayloadSize>
        <NoOfFrames>1</NoOfFrames>
        <Source name="ES_CTRL2" />
        <Destinations>
            <Dest name="ES_FRONT_RAD" />
        </Destinations>
        <Deadline>2000</Deadline>
    </AVBApplication>
    <AVBApplication name="AVB_27">
        <AVBClass>CLASS_A</AVBClass>
        <PayloadSize>469</PayloadSize>
        <NoOfFrames>1</NoOfFrames>
        <Source name="ES_CTRL1" />
        <Destinations>
            <Dest name="ES_ECM" />
        </Destinations>
        <Deadline>2000</Deadline>
    </AVBApplication>
    <AVBApplication name="AVB_28">
        <AVBClass>CLASS_A</AVBClass>
        <PayloadSize>796</PayloadSize>
        <NoOfFrames>1</NoOfFrames>
        <Source name="ES_CTRL1" />
        <Destinations>
            <Dest name="ES_EBCM" />
        </Destinations>
        <Deadline>2000</Deadline>
    </AVBApplication>
    <AVBApplication name="AVB_29">
        <AVBClass>CLASS_A</AVBClass>
        <PayloadSize>677</PayloadSize>
        <NoOfFrames>1</NoOfFrames>
        <Source name="ES_CTRL2" />
        <Destinations>
            <Dest name="ES_ECM" />
        </Destinations>
        <Deadline>2000</Deadline>
    </AVBApplication>
    <AVBApplication name="AVB_30">
        <AVBClass>CLASS_A</AVBClass>
        <PayloadSize>995</PayloadSize>
        <NoOfFrames>1</NoOfFrames>
        <Source name="ES_CTRL2" />
        <Destinations>
            <Dest name="ES_EBCM" />
        </Destinations>
        <Deadline>2000</Deadline>
    </AVBApplication>
    <AVBApplication name="AVB_31">
        <AVBClass>CLASS_A</AVBClass>
        <PayloadSize>525</PayloadSize>
        <NoOfFrames>1</NoOfFrames>
        <Source name="ES_ECM" />
        <Destinations>
            <Dest name="ES_CTRL2" />
        </Destinations>
        <Deadline>2000</Deadline>
    </AVBApplication>
    <AVBApplication name="AVB_32">
        <AVBClass>CLASS_A</AVBClass>
        <PayloadSize>1272</PayloadSize>
        <NoOfFrames>1</NoOfFrames>
        <Source name="ES_ECM" />
        <Destinations>
            <Dest name="ES_CTRL1" />
        </Destinations>
        <Deadline>2000</Deadline>
    </AVBApplication>
    <AVBApplication name="AVB_33">
        <AVBClass>CLASS_A</AVBClass>
        <PayloadSize>170</PayloadSize>
        <NoOfFrames>1</NoOfFrames>
        <Source name="ES_EBCM" />
        <Destinations>
            <Dest name="ES_CTRL2" />
        </Destinations>
        <Deadline>2000</Deadline>
    </AVBApplication>
    <AVBApplication name="AVB_34">
        <AVBClass>CLASS_A</AVBClass>
        <PayloadSize>440</PayloadSize>
        <NoOfFrames>1</NoOfFrames>
        <Source name="ES_EBCM" />
        <Destinations>
            <Dest name="ES_CTRL1" />
        </Destinations>
        <Deadline>2000</Deadline>
    </AVBApplication>
    <AVBApplication name="AVB_35">
        <AVBClass>CLASS_A</AVBClass>
        <PayloadSize>734</PayloadSize>
        <NoOfFrames>1</NoOfFrames>
        <Source name="ES_CTRL1" />
        <Destinations>
            <Dest name="ES_EPS" />
        </Destinations>
        <Deadline>2000</Deadline>
    </AVBApplication>
    <AVBApplication name="AVB_36">
        <AVBClass>CLASS_A</AVBClass>
        <PayloadSize>891</PayloadSize>
        <NoOfFrames>1</NoOfFrames>
        <Source name="ES_CTRL2" />
        <Destinations>
            <Dest name="ES_EPS" />
        </Destinations>
        <Deadline>2000</Deadline>
    </AVBApplication>
    <AVBApplication name="AVB_37">
        <AVBClass>CLASS_A</AVBClass>
        <PayloadSize>955</PayloadSize>
        <NoOfFrames>1</NoOfFrames>
        <Source name="ES_EPS" />
        <Destinations>
            <Dest name="ES_CTRL1" />
        </Destinations>
        <Deadline>2000</Deadline>
    </AVBApplication>
    <AVBApplication name="AVB_38">
        <AVBClass>CLASS_A</AVBClass>
        <PayloadSize>856</PayloadSize>
        <NoOfFrames>1</NoOfFrames>
        <Source name="ES_EPS" />
        <Destinations>
            <Dest name="ES_CTRL2" />
        </Destinations>
        <Deadline>2000</Deadline>
    </AVBApplication>
    <AVBApplication name="AVB_39">
        <AVBClass>CLASS_A</AVBClass>
        <PayloadSize>299</PayloadSize>
        <NoOfFrames>1</NoOfFrames>
        <Source name="ES_IMU1" />
        <Destinations>
            <Dest name="ES_CTRL2" />
        </Destinations>
        <Deadline>2000</Deadline>
    </AVBApplication>
    <AVBApplication name="AVB_40">
        <AVBClass>CLASS_A</AVBClass>
        <PayloadSize>477</PayloadSize>
        <NoOfFrames>1</NoOfFrames>
        <Source name="ES_IMU1" />
        <Destinations>
            <Dest name="ES_MAPLOC" />
        </Destinations>
        <Deadline>2000</Deadline>
    </AVBApplication>
    <AVBApplication name="AVB_41">
        <AVBClass>CLASS_A</AVBClass>
        <PayloadSize>806</PayloadSize>
        <NoOfFrames>1</NoOfFrames>
        <Source name="ES_IMU1" />
        <Destinations>
            <Dest name="ES_CTRL1" />
        </Destinations>
        <Deadline>2000</Deadline>
    </AVBApplication>
    <AVBApplication name="AVB_42">
        <AVBClass>CLASS_A</AVBClass>
        <PayloadSize>857</PayloadSize>
        <NoOfFrames>1</NoOfFrames>
        <Source name="ES_IMU2" />
        <Destinations>
            <Dest name="ES_CTRL2" />
        </Destinations>
        <Deadline>2000</Deadline>
    </AVBApplication>
    <AVBApplication name="AVB_43">
        <AVBClass>CLASS_A</AVBClass>
        <PayloadSize>678</PayloadSize>
        <NoOfFrames>1</NoOfFrames>
        <Source name="ES_IMU2" />
        <Destinations>
            <Dest name="ES_MAPLOC" />
        </Destinations>
        <Deadline>2000</Deadline>
    </AVBApplication>
    <AVBApplication name="AVB_44">
        <AVBClass>CLASS_A</AVBClass>
        <PayloadSize>717</PayloadSize>
        <NoOfFrames>1</NoOfFrames>
        <Source name="ES_IMU2" />
        <Destinations>
            <Dest name="ES_CTRL1" />
        </Destinations>
        <Deadline>2000</Deadline>
    </AVBApplication>
    <AVBApplication name="AVB_45">
        <AVBClass>CLASS_A</AVBClass>
        <PayloadSize>1439</PayloadSize>
        <NoOfFrames>1</NoOfFrames>
        <Source name="ES_MAPLOC" />
        <Destinations>
            <Dest name="ES_CTRL2" />
        </Destinations>
        <Deadline>2000</Deadline>
    </AVBApplication>
    <AVBApplication name="AVB_46">
        <AVBClass>CLASS_A</AVBClass>
        <PayloadSize>808</PayloadSize>
        <NoOfFrames>1</NoOfFrames>
        <Source name="ES_MAPLOC" />
        <Destinations>
            <Dest name="ES_CTRL1" />
        </Destinations>
        <Deadline>2000</Deadline>
    </AVBApplication>
    <AVBApplication name="AVB_47">
        <AVBClass>CLASS_A</AVBClass>
        <PayloadSize>250</PayloadSize>
        <NoOfFrames>1</NoOfFrames>
        <Source name="ES_MAPLOC" />
        <Destinations>
            <Dest name="ES_FRONT_CAM" />
        </Destinations>
        <Deadline>2000</Deadline>
    </AVBApplication>
    <AVBApplication name="AVB_48">
        <AVBClass>CLASS_A</AVBClass>
        <PayloadSize>746</PayloadSize>
        <NoOfFrames>1</NoOfFrames>
        <Source name="ES_FRONT_CAM" />
        <Destinations>
            <Dest name="ES_MAPLOC" />
        </Destinations>
        <Deadline>2000</Deadline>
    </AVBApplication>
    <TTApplication name="TT1">
        <Source name="ES_CTRL1">
            <Destinations>
                <GCL offset="0" duration="10.0" frequency="2" />
                <Dest name="ES_ECM">
                    <Route>
                        <Bridge name="SW_B18" />
                        <Bridge name="SW_B20_1" />
                    </Route>
                </Dest>
            </Destinations>
        </Source>
    </TTApplication>
    <TTApplication name="TT2">
        <Source name="ES_CTRL1">
            <Destinations>
                <GCL offset="10.4" duration="10.0" frequency="3" />
                <Dest name="ES_EBCM">
                    <Route>
                        <Bridge name="SW_B18_1" />
                        <Bridge name="SW_B20" />
                        <Bridge name="SW_B17" />
                    </Route>
                </Dest>
            </Destinations>
        </Source>
    </TTApplication>
    <TTApplication name="TT3">
        <Source name="ES_CTRL2">
            <Destinations>
                <GCL offset="0" duration="10.0" frequency="2" />
                <Dest name="ES_FRONT_RAD">
                    <Route>
                        <Bridge name="SW_B19" />
                        <Bridge name="SW_B10_1" />
                    </Route>
                </Dest>
            </Destinations>
        </Source>
    </TTApplication>
    <TTApplication name="TT4">
        <Source name="ES_CTRL2">
            <Destinations>
                <GCL offset="0" duration="10.0" frequency="2" />
                <Dest name="ES_FRONT_CAM">
                    <Route>
                        <Bridge name="SW_B19_1" />
                        <Bridge name="SW_B1" />
                    </Route>
                </Dest>
            </Destinations>
        </Source>
    </TTApplication>
    <TTApplication name="TT5">
        <Source name="ES_FRONT_CAM">
            <Destinations>
                <GCL offset="10.4" duration="10.0" frequency="4" />
                <Dest name="ES_CTRL1">
                    <Route>
                        <Bridge name="SW_B1_1" />
                        <Bridge name="SW_B19" />
                        <Bridge name="SW_B20" />
                        <Bridge name="SW_B18" />
                    </Route>
                </Dest>
            </Destinations>
        </Source>
    </TTApplication>
    <TTApplication name="TT6">
        <Source name="ES_REAR_CAM">
            <Destinations>
                <GCL offset="10.4" duration="10.0" frequency="2" />
                <Dest name="ES_CTRL1">
                    <Route>
                        <Bridge name="SW_B5_1" />
                        <Bridge name="SW_B13" />
                        <Bridge name="SW_B19_1" />
                        <Bridge name="SW_B1_1" />
                        <Bridge name="SW_B18_1" />
                    </Route>
                </Dest>
            </Destinations>
        </Source>
    </TTApplication>
    <TTApplication name="TT7">
        <Source name="ES_FRONT_CAM">
            <Destinations>
                <GCL offset="10.4" duration="10.0" frequency="3" />
                <Dest name="ES_CTRL2">
                    <Route>
                        <Bridge name="SW_B1" />
                        <Bridge name="SW_B18" />
                        <Bridge name="SW_B20" />
                        <Bridge name="SW_B6" />
                        <Bridge name="SW_B20_1" />
                        <Bridge name="SW_B19" />
                    </Route>
                </Dest>
            </Destinations>
        </Source>
    </TTApplication>
    <TTApplication name="TT8">
        <Source name="ES_REAR_CAM">
            <Destinations>
                <GCL offset="10.4" duration="10.0" frequency="3" />
                <Dest name="ES_CTRL2">
                    <Route>
                        <Bridge name="SW_B5" />
                        <Bridge name="SW_B13_1" />
                        <Bridge name="SW_B19_1" />
                    </Route>
                </Dest>
            </Destinations>
        </Source>
    </TTApplication>
</Applications>